alp/__init__.py
alp/alp_module.py
alp/interfaces/error.py
alp/interfaces/transmittion.py
alp/provider.py
alp/receiver.py
alp/receiver_service.py
alp/transmitter_module.py
alp/transmitter_service.py
alp/utils/parser.py
alp/utils/validation.py
ascender_alp-0.0.2.dist-info/LICENSE
ascender_alp-0.0.2.dist-info/METADATA
ascender_alp-0.0.2.dist-info/WHEEL
ascender_alp-0.0.2.dist-info/RECORD
