Metadata-Version: 2.3
Name: ascender-alp
Version: 0.0.2
Summary: Ascender LiveAPI Protocol - for live API communication.
Author: Zahcoder34
Author-email: Zakhriw@gmail.com
Requires-Python: >=3.11,<3.14
Classifier: Programming Language :: Python :: 3
Classifier: Programming Language :: Python :: 3.11
Classifier: Programming Language :: Python :: 3.12
Classifier: Programming Language :: Python :: 3.13
Requires-Dist: ascender-framework (>=2.0rc6,<3.0)
Requires-Dist: python-socketio (>=5.13.0,<6.0.0)
